accept/__init__.py
accept/endpoints.py
accept/payment.py
accept/version.py
accept_paymob-1.0.0.dist-info/LICENSE
accept_paymob-1.0.0.dist-info/METADATA
accept_paymob-1.0.0.dist-info/WHEEL
accept_paymob-1.0.0.dist-info/top_level.txt
accept_paymob-1.0.0.dist-info/RECORD
