Metadata-Version: 2.1
Name: accept-paymob
Version: 1.0.0
Summary: Python client for the Paymob.accept API
Home-page: https://github.com/Shokr/paymob.accept
Author: Muhammed Shokr
Author-email: mohamedshokr@paymob.com
License: MIT
Project-URL: Documentation, https://docs.paymob.com/
Project-URL: Source Code, https://github.com/Shokr/paymob.accept
Keywords: Paymob Accept api payments
Platform: UNKNOWN
Classifier: Development Status :: 5 - Production/Stable
Classifier: Intended Audience :: Developers
Classifier: License :: OSI Approved :: MIT License
Classifier: Operating System :: OS Independent
Classifier: Programming Language :: Python :: 3
Classifier: Programming Language :: Python :: 3.4
Classifier: Programming Language :: Python :: 3.5
Classifier: Programming Language :: Python :: 3.6
Classifier: Programming Language :: Python :: 3.7
Classifier: Programming Language :: Python :: 3.8
Classifier: Programming Language :: Python :: 3.9
Classifier: Programming Language :: Python :: Implementation :: PyPy
Classifier: Topic :: Software Development :: Libraries :: Python Modules
Requires-Python: >=3
